LICENSE.txt
MANIFEST.in
README.txt
setup.py
dbms/__init__.py
dbms/connect.py
dbms/cursors.py
dbms/probe.py
dbms/schema.py
dbms/settings.py
dbms/utils.py
dbms.egg-info/PKG-INFO
dbms.egg-info/SOURCES.txt
dbms.egg-info/dependency_links.txt
dbms.egg-info/requires.txt
dbms.egg-info/top_level.txt
docs/_sources/dbms.txt
docs/_sources/index.txt