Metadata-Version: 1.1
Name: dbms
Version: 1.1.1
Summary: DataBases Made Simpler - Uniform interface for multiple adapters
Home-page: https://sourceforge.net/projects/pydbms/
Author: Scott Bailey
Author-email: scottrbailey@gmail.com
License: LICENSE.txt
Keywords: database dbms rdbms Oracle PostgreSQL MySQL SQLServer Firebird DB2 SQLite ODBC
Platform: UNKNOWN
Classifier: Development Status :: 5 - Production/Stable
Classifier: Environment :: Console
Classifier: License :: OSI Approved :: BSD License
Classifier: Programming Language :: Python :: 2.6
Classifier: Programming Language :: Python :: 2.7
Classifier: Programming Language :: Python :: 3
Classifier: Programming Language :: Python :: 3.1
Classifier: Programming Language :: Python :: 3.2
Classifier: Programming Language :: Python :: 3.3
Classifier: Programming Language :: Python :: 3.4
Classifier: Programming Language :: SQL
Classifier: Intended Audience :: Developers
Classifier: Intended Audience :: Information Technology
Classifier: Intended Audience :: Science/Research
Classifier: Topic :: Database
Classifier: Natural Language :: English
Classifier: Operating System :: OS Independent
